{".env":[".env"],"assets/abi/Block4SC.json":["assets/abi/Block4SC.json"],"assets/abi/HelloName.json":["assets/abi/HelloName.json"],"assets/img/B4SC_icon_40.png":["assets/img/B4SC_icon_40.png"],"assets/img/B4SC_icon_512.png":["assets/img/B4SC_icon_512.png"],"assets/img/icon_Block4SC.jpg":["assets/img/icon_Block4SC.jpg"],"assets/img/javi%20(copy).jpg":["assets/img/javi%20(copy).jpg"],"assets/img/javi.png":["assets/img/javi.png"],"assets/img/logo_orosus.png":["assets/img/logo_orosus.png"],"assets/img/screenshot_containers.png":["assets/img/screenshot_containers.png"],"assets/img/screenshot_locations.png":["assets/img/screenshot_locations.png"],"assets/img/screenshot_menu.png":["assets/img/screenshot_menu.png"],"assets/img/screenshot_stocks.png":["assets/img/screenshot_stocks.png"],"assets/img/screenshot_transport.png":["assets/img/screenshot_transport.png"],"packages/cupertino_icons/assets/CupertinoIcons.ttf":["packages/cupertino_icons/assets/CupertinoIcons.ttf"]}